airflow_dags/__init__.py
airflow_dags/airflow_change_ods_dpn.py
airflow_dags/airflow_change_ods_ga.py
airflow_dags/airflow_change_ods_pnt.py
airflow_dags/airflow_change_procedure.py
airflow_dags/airflow_checkrows.py
airflow_dags/airflow_daily_ods_dpn.py
airflow_dags/airflow_daily_ods_ga.py
airflow_dags/airflow_daily_ods_ga_backup.py
airflow_dags/airflow_daily_ods_pnt.py
airflow_dags/airflow_drpnt.py
airflow_dags/airflow_gadpn.py
airflow_dags/airflow_gadpn_hourly.py
airflow_dags/airflow_gapnt.py
airflow_dags/airflow_gapnt_hourly.py
airflow_dags/airflow_gcwb_ods.py
airflow_dags/airflow_individual_ga.py
airflow_dags/airflow_init_pntshop.py
airflow_dags/airflow_init_procedure.py
airflow_dags/airflow_init_procedure_behavior.py
airflow_dags/airflow_init_procedure_category.py
airflow_dags/airflow_init_procedure_code.py
airflow_dags/airflow_init_procedure_common.py
airflow_dags/airflow_init_procedure_coupon.py
airflow_dags/airflow_init_procedure_current_city.py
airflow_dags/airflow_init_procedure_etc.py
airflow_dags/airflow_init_procedure_goal.py
airflow_dags/airflow_init_procedure_health_topic.py
airflow_dags/airflow_init_procedure_product.py
airflow_dags/airflow_init_procedure_rest.py
airflow_dags/airflow_init_procedure_search.py
airflow_dags/airflow_pntshop.py
airflow_dags/airflow_snowflake.py
airflow_dags/airflow_snowflake_MSTD_BASE_MM.py
airflow_dags/airflow_variable.py
commonlibs/__init__.py
commonlibs/pdutils.py
commonlibs/prac_py.py
commonlibs/utils.py
gcwb_dataload/GA_API_Data_DPN.py
gcwb_dataload/GA_API_Data_PNT.py
gcwb_dataload/__init__.py
gcwb_dataload/drpnt_daily.py
gcwb_dataload/drpnt_init.py
gcwb_dataload/ga_dataload.py
gcwb_dataload/pntshop_crawler.py
gcwb_dataload/pntshop_init.py
gcwb_dataload/pntshop_monthly.py
gcwb_dataload/ga/DPN_AFFINITY.py
gcwb_dataload/ga/DPN_AGE.py
gcwb_dataload/ga/DPN_BEHAVIOR.py
gcwb_dataload/ga/DPN_CLIENT.py
gcwb_dataload/ga/DPN_CLIENT_CITY.py
gcwb_dataload/ga/DPN_GENDER.py
gcwb_dataload/ga/DPN_GOAL.py
gcdp-0.0.1.dist-info/LICENSE
gcdp-0.0.1.dist-info/METADATA
gcdp-0.0.1.dist-info/WHEEL
gcdp-0.0.1.dist-info/top_level.txt
gcdp-0.0.1.dist-info/RECORD
